{
  "9": {
    "id": 9,
    "name": "教一",
    "campusId": 22
  },
  "10": {
    "id": 10,
    "name": "教二",
    "campusId": 22
  },
  "11": {
    "id": 11,
    "name": "教三",
    "campusId": 22
  },
  "12": {
    "id": 12,
    "name": "教四",
    "campusId": 22
  },
  "13": {
    "id": 13,
    "name": "教五",
    "campusId": 22
  },
  "14": {
    "id": 14,
    "name": "教六",
    "campusId": 22
  },
  "15": {
    "id": 15,
    "name": "教七",
    "campusId": 22
  },
  "45": {
    "id": 45,
    "name": "教八",
    "campusId": 22
  },
  "114": {
    "id": 114,
    "name": "礼东",
    "campusId": 24
  },
  "115": {
    "id": 115,
    "name": "中山院",
    "campusId": 24
  },
  "116": {
    "id": 116,
    "name": "东南院",
    "campusId": 24
  },
  "117": {
    "id": 117,
    "name": "九龙湖纪忠楼",
    "campusId": 23
  },
  "118": {
    "id": 118,
    "name": "前工院",
    "campusId": 24
  },
  "119": {
    "id": 119,
    "name": "无锡分校致知堂",
    "campusId": 27
  }
}